scrapy_scraper/main.py
scrapy_scraper/utils/array.py
scrapy_scraper/utils/config.py
scrapy_scraper/utils/cookie.py
scrapy_scraper/utils/directory.py
scrapy_scraper/utils/file.py
scrapy_scraper/utils/general.py
scrapy_scraper/utils/header.py
scrapy_scraper/utils/scrape.py
scrapy_scraper/utils/stopwatch.py
scrapy_scraper/utils/url.py
scrapy_scraper/utils/validate.py
scrapy_scraper-3.7.dist-info/licenses/LICENSE
scrapy_scraper-3.7.dist-info/METADATA
scrapy_scraper-3.7.dist-info/WHEEL
scrapy_scraper-3.7.dist-info/entry_points.txt
scrapy_scraper-3.7.dist-info/top_level.txt
scrapy_scraper-3.7.dist-info/RECORD
