Metadata-Version: 2.4
Name: scrapy-scraper
Version: 3.7
Summary: Web crawler and scraper based on Scrapy and Playwright's headless browser.
Author: Ivan Sincek
Project-URL: Homepage, https://github.com/ivan-sincek/scrapy-scraper
Classifier: Programming Language :: Python :: 3
Classifier: License :: OSI Approved :: MIT License
Classifier: Operating System :: OS Independent
Requires-Python: >=3.10
License-File: LICENSE
Requires-Dist: beautifulsoup4>=4.12.3
Requires-Dist: bot-safe-agents>=1.0
Requires-Dist: colorama>=0.4.6
Requires-Dist: jsbeautifier>=1.14.11
Requires-Dist: playwright>=1.49.0
Requires-Dist: scrapy>=2.12.0
Requires-Dist: scrapy-playwright>=0.0.42
Requires-Dist: termcolor>=2.4.0
Requires-Dist: tldextract>=3.6.0
Dynamic: license-file
